Compiled from "Concatenation.java"
public class com.nbcb.thinkingInJava.strings.basic.Concatenation {
  public com.nbcb.thinkingInJava.strings.basic.Concatenation();
    Code:
       0: aload_0
       1: invokespecial #1                  // Method java/lang/Object."<init>":()V
       4: return

  public static void main(java.lang.String[]);
    Code:
       0: getstatic     #2                  // Field java/lang/System.out:Ljava/io/PrintStream;
       3: ldc           #3                  // String start Concatenation ...
       5: invokevirtual #4                  // Method java/io/PrintStream.println:(Ljava/lang/String;)V
       8: ldc           #5                  // String hello
      10: astore_1
      11: new           #6                  // class java/lang/StringBuilder
      14: dup
      15: invokespecial #7                  // Method java/lang/StringBuilder."<init>":()V
      18: ldc           #8                  // String gogogo
      20: invokevirtual #9                  // Method java/lang/StringBuilder.append:(Ljava/lang/String;)Ljava/lang/StringBuilder;
      23: aload_1
      24: invokevirtual #9                  // Method java/lang/StringBuilder.append:(Ljava/lang/String;)Ljava/lang/StringBuilder;
      27: ldc           #10                 // String  world ...
      29: invokevirtual #9                  // Method java/lang/StringBuilder.append:(Ljava/lang/String;)Ljava/lang/StringBuilder;
      32: sipush        12347
      35: invokevirtual #11                 // Method java/lang/StringBuilder.append:(I)Ljava/lang/StringBuilder;
      38: invokevirtual #12                 // Method java/lang/StringBuilder.toString:()Ljava/lang/String;
      41: astore_2
      42: getstatic     #2                  // Field java/lang/System.out:Ljava/io/PrintStream;
      45: aload_2
      46: invokevirtual #4                  // Method java/io/PrintStream.println:(Ljava/lang/String;)V
      49: return
}
